djeff/djeff.py
djeff/__init__.py
djeff/middleware.py
djeff-0.1.1.dist-info/WHEEL
djeff-0.1.1.dist-info/RECORD
djeff-0.1.1.dist-info/DESCRIPTION.rst
djeff-0.1.1.dist-info/METADATA
djeff-0.1.1.dist-info/top_level.txt
djeff-0.1.1.dist-info/metadata.json
