Metadata-Version: 2.0
Name: djeff
Version: 0.1.1
Summary: Add silent D's to all the things (or just the things you want)
Home-page: https://github.com/lightstrike/djeff
Author: Geoffrey Sechter
Author-email: geoffrey.sechter@gmail.com
License: ISCL
Keywords: djeff
Platform: UNKNOWN
Classifier: Development Status :: 2 - Pre-Alpha
Classifier: Intended Audience :: Developers
Classifier: License :: OSI Approved :: ISC License (ISCL)
Classifier: Natural Language :: English
Classifier: Programming Language :: Python :: 2
Classifier: Programming Language :: Python :: 2.6
Classifier: Programming Language :: Python :: 2.7
Classifier: Programming Language :: Python :: 3
Classifier: Programming Language :: Python :: 3.3
Classifier: Programming Language :: Python :: 3.4
